netaddr/__init__.py
netaddr/cli.py
netaddr/compat.py
netaddr/core.py
netaddr/fbsocket.py
netaddr/contrib/__init__.py
netaddr/contrib/subnet_splitter.py
netaddr/eui/__init__.py
netaddr/eui/iab.idx
netaddr/eui/iab.txt
netaddr/eui/ieee.py
netaddr/eui/oui.idx
netaddr/eui/oui.txt
netaddr/ip/__init__.py
netaddr/ip/glob.py
netaddr/ip/iana.py
netaddr/ip/ipv4-address-space.xml
netaddr/ip/ipv6-address-space.xml
netaddr/ip/ipv6-unicast-address-assignments.xml
netaddr/ip/multicast-addresses.xml
netaddr/ip/nmap.py
netaddr/ip/rfc1924.py
netaddr/ip/sets.py
netaddr/strategy/__init__.py
netaddr/strategy/eui48.py
netaddr/strategy/eui64.py
netaddr/strategy/ipv4.py
netaddr/strategy/ipv6.py
netaddr/tests/__init__.py
netaddr/tests/test_netaddr.py
netaddr/tests/core/__init__.py
netaddr/tests/core/test_pubsub.py
netaddr/tests/eui/__init__.py
netaddr/tests/eui/sample_iab.txt
netaddr/tests/eui/sample_oui.txt
netaddr/tests/eui/test_eui.py
netaddr/tests/eui/test_ieee_parsers.py
netaddr/tests/ip/__init__.py
netaddr/tests/ip/test_cidr_v4.py
netaddr/tests/ip/test_cidr_v6.py
netaddr/tests/ip/test_dns.py
netaddr/tests/ip/test_ip.py
netaddr/tests/ip/test_ip_categories.py
netaddr/tests/ip/test_ip_comparisons.py
netaddr/tests/ip/test_ip_globs.py
netaddr/tests/ip/test_ip_network_categories.py
netaddr/tests/ip/test_ip_ranges.py
netaddr/tests/ip/test_ip_rfc1924.py
netaddr/tests/ip/test_ip_sets.py
netaddr/tests/ip/test_ip_splitter.py
netaddr/tests/ip/test_ip_v4.py
netaddr/tests/ip/test_ip_v4_v6_conversions.py
netaddr/tests/ip/test_ip_v6.py
netaddr/tests/ip/test_network_ops.py
netaddr/tests/ip/test_nmap.py
netaddr/tests/ip/test_old_specs.py
netaddr/tests/ip/test_platform_osx.py
netaddr/tests/ip/test_socket_module_fallback.py
netaddr/tests/strategy/__init__.py
netaddr/tests/strategy/test_eui48_strategy.py
netaddr/tests/strategy/test_ipv4_strategy.py
netaddr/tests/strategy/test_ipv6_strategy.py
netaddr-1.2.1.dist-info/AUTHORS.rst
netaddr-1.2.1.dist-info/LICENSE.rst
netaddr-1.2.1.dist-info/METADATA
netaddr-1.2.1.dist-info/WHEEL
netaddr-1.2.1.dist-info/entry_points.txt
netaddr-1.2.1.dist-info/top_level.txt
netaddr-1.2.1.dist-info/RECORD
