Metadata-Version: 2.1
Name: netaddr
Version: 1.2.1
Summary: A network address manipulation library for Python
Author-email: "David P. D. Moss" <josiah_carberry@brown.edu>, Stefan Nordhausen <stefan.nordhausen@immobilienscout24.de>
Maintainer-email: Jakub Stasiak <jakub@stasiak.at>
License: BSD License
Project-URL: Documentation, https://netaddr.readthedocs.io/en/latest/
Project-URL: Download, https://pypi.org/project/netaddr/
Project-URL: Repository, https://github.com/netaddr/netaddr/
Project-URL: Changelog, https://netaddr.readthedocs.io/en/latest/changes.html
Project-URL: Issue tracker, https://github.com/netaddr/netaddr/issues
Keywords: Networking,Systems Administration,IANA,IEEE,CIDR,IP,IPv4,IPv6,CIDR,EUI,MAC,MAC-48,EUI-48,EUI-64
Classifier: Development Status :: 5 - Production/Stable
Classifier: Environment :: Console
Classifier: Intended Audience :: Developers
Classifier: Intended Audience :: Education
Classifier: Intended Audience :: Information Technology
Classifier: Intended Audience :: Science/Research
Classifier: Intended Audience :: System Administrators
Classifier: Intended Audience :: Telecommunications Industry
Classifier: License :: OSI Approved :: BSD License
Classifier: Natural Language :: English
Classifier: Operating System :: OS Independent
Classifier: Programming Language :: Python
Classifier: Programming Language :: Python :: 3
Classifier: Programming Language :: Python :: 3.7
Classifier: Programming Language :: Python :: 3.8
Classifier: Programming Language :: Python :: 3.9
Classifier: Programming Language :: Python :: 3.10
Classifier: Programming Language :: Python :: 3.11
Classifier: Topic :: Communications
Classifier: Topic :: Documentation
Classifier: Topic :: Education
Classifier: Topic :: Education :: Testing
Classifier: Topic :: Home Automation
Classifier: Topic :: Internet
Classifier: Topic :: Internet :: Log Analysis
Classifier: Topic :: Internet :: Name Service (DNS)
Classifier: Topic :: Internet :: Proxy Servers
Classifier: Topic :: Internet :: WWW/HTTP
Classifier: Topic :: Internet :: WWW/HTTP :: Indexing/Search
Classifier: Topic :: Internet :: WWW/HTTP :: Site Management
Classifier: Topic :: Security
Classifier: Topic :: Software Development
Classifier: Topic :: Software Development :: Libraries
Classifier: Topic :: Software Development :: Libraries :: Python Modules
Classifier: Topic :: Software Development :: Quality Assurance
Classifier: Topic :: Software Development :: Testing
Classifier: Topic :: Software Development :: Testing :: Traffic Generation
Classifier: Topic :: System :: Benchmark
Classifier: Topic :: System :: Clustering
Classifier: Topic :: System :: Distributed Computing
Classifier: Topic :: System :: Installation/Setup
Classifier: Topic :: System :: Logging
Classifier: Topic :: System :: Monitoring
Classifier: Topic :: System :: Networking
Classifier: Topic :: System :: Networking :: Firewalls
Classifier: Topic :: System :: Networking :: Monitoring
Classifier: Topic :: System :: Networking :: Time Synchronization
Classifier: Topic :: System :: Recovery Tools
Classifier: Topic :: System :: Shells
Classifier: Topic :: System :: Software Distribution
Classifier: Topic :: System :: Systems Administration
Classifier: Topic :: System :: System Shells
Classifier: Topic :: Text Processing
Classifier: Topic :: Text Processing :: Filters
Classifier: Topic :: Utilities
Requires-Python: >=3.7
License-File: LICENSE.rst
License-File: AUTHORS.rst
Provides-Extra: nicer-shell
Requires-Dist: ipython; extra == "nicer-shell"
